ramps_majestic/__init__.py
ramps_majestic/__init__v1.py
ramps_majestic/status_1.py
ramps_majestic/_clique/__init__.py
ramps_majestic/_clique/group/__init__.py
ramps_majestic/_licenses/gpl-3.0-standalone.html
ramps_majestic/_status/status.proc.py
ramps_majestic/_status/vows/1/status_1.py
ramps_majestic/_status/vows/2/status_1.py
ramps_majestic/_status/vows/3/status_1.py
ramps_majestic/charts/VLOCH.py
ramps_majestic/charts/majestic_line.py
ramps_majestic/charts/trend_side_circles.py
ramps_majestic/charts/annotations/vline.py
ramps_majestic/charts/shapes/rectangle.py
ramps_majestic/charts/shapes/vline.py
ramps_majestic/example_data/read.py
ramps_majestic/furniture/places.py
ramps_majestic/furniture/CSV/read.py
ramps_majestic/furniture/DF/reverse.py
ramps_majestic/tendencies/majestic/__init__.py
ramps_majestic/victory_multiplier/purchase_treasure_at_inclines.py
ramps_majestic/victory_multiplier/purchase_treasure_over_span.py
ramps_majestic/victory_multiplier/ramp_v1.py
ramps_majestic/victory_multiplier/ramp_v2.py
ramps_majestic-1.0.1.dist-info/METADATA
ramps_majestic-1.0.1.dist-info/WHEEL
ramps_majestic-1.0.1.dist-info/top_level.txt
ramps_majestic-1.0.1.dist-info/RECORD
