Metadata-Version: 2.1
Name: ramps_majestic
Version: 1.0.1
License: GPL 3.0
Requires-Dist: bracelet
Requires-Dist: click
Requires-Dist: pandas
Requires-Dist: plotly
Requires-Dist: rich
